catbars/__init__.py
catbars/bars.py
catbars/cac40.py
catbars/conf.py
catbars/models.py
catbars-1.0.1.dist-info/LICENSE.txt
catbars-1.0.1.dist-info/LICENSE.txt~
catbars-1.0.1.dist-info/METADATA
catbars-1.0.1.dist-info/WHEEL
catbars-1.0.1.dist-info/top_level.txt
catbars-1.0.1.dist-info/RECORD
