Metadata-Version: 2.1
Name: catbars
Version: 1.0.1
Summary: A plotting library for making horizontal bar charts.
Home-page: https://github.com/ConstantinLenoir/catbars
Author: Constantin Yves Lenoir
Author-email: constantinlenoir@gmail.com
License: UNKNOWN
Platform: UNKNOWN
Classifier: Programming Language :: Python :: 3
Classifier: License :: OSI Approved :: MIT License
Classifier: Operating System :: OS Independent
Requires-Python: >=3.0
Requires-Dist: matplotlib
Requires-Dist: numpy
